{"textures":{"0":"modelengine:entity/bloodbound_barrier_long","particle":"#0"},"elements":[{"from":[2.796875,-10.006855,13.656855],"to":[13.203125,1.0931454,13.656855],"faces":{"south":{"uv":[10.6875,7.5,9.375,8.875],"tintindex":0,"rotation":0,"texture":"#0"},"north":{"uv":[9.375,7.5,10.6875,8.875],"tintindex":0,"rotation":0,"texture":"#0"}},"rotation":{"origin":[5.8031254,1.2000008,8.0],"angle":45.0,"axis":"x"}}],"display":{"head":{"rotation":[0.0,0.0,0.0]},"firstperson_righthand":{"rotation":[0.0,0.0,0.0]},"thirdperson_lefthand":{"rotation":[0.0,-0.0,-0.0]},"firstperson_lefthand":{"rotation":[0.0,-0.0,-0.0]},"fixed":{"rotation":[0.0,0.0,0.0]},"ground":{"rotation":[0.0,0.0,0.0]},"thirdperson_righthand":{"rotation":[0.0,0.0,0.0]},"gui":{"rotation":[-150.0,-45.0,180.0]}}}