{"textures":{"0":"modelengine:entity/teacherchair","particle":"#0"},"elements":[{"from":[7.234086,5.75,3.0213108],"to":[9.734085,8.25,4.021311],"faces":{"east":{"uv":[12.5,2.25,12.75,3.0],"tintindex":0,"rotation":0,"texture":"#0"},"south":{"uv":[1.5,11.75,2.25,12.5],"tintindex":0,"rotation":0,"texture":"#0"},"north":{"uv":[0.75,11.75,1.5,12.5],"tintindex":0,"rotation":0,"texture":"#0"},"west":{"uv":[3.0,12.5,3.25,13.25],"tintindex":0,"rotation":0,"texture":"#0"},"up":{"uv":[13.25,3.25,12.5,3.0],"tintindex":0,"rotation":0,"texture":"#0"},"down":{"uv":[13.25,3.25,12.5,3.5],"tintindex":0,"rotation":0,"texture":"#0"}},"rotation":{"origin":[2.5,9.0,7.0000005],"angle":-45.0,"axis":"y"}},{"from":[2.5151882,8.25,6.0586586],"to":[8.765188,9.75,7.5586586],"faces":{"east":{"uv":[12.0,8.5,12.5,9.0],"tintindex":0,"rotation":0,"texture":"#0"},"south":{"uv":[0.75,11.25,2.25,11.75],"tintindex":0,"rotation":0,"texture":"#0"},"north":{"uv":[10.75,11.0,12.25,11.5],"tintindex":0,"rotation":0,"texture":"#0"},"west":{"uv":[12.0,9.0,12.5,9.5],"tintindex":0,"rotation":0,"texture":"#0"},"up":{"uv":[3.75,11.75,2.25,11.25],"tintindex":0,"rotation":0,"texture":"#0"},"down":{"uv":[12.75,4.5,11.25,5.0],"tintindex":0,"rotation":0,"texture":"#0"}},"rotation":{"origin":[2.5,9.0,7.0000005],"angle":-22.5,"axis":"y"}},{"from":[7.234086,5.75,5.021311],"to":[9.734085,8.25,6.021311],"faces":{"east":{"uv":[3.25,12.5,3.5,13.25],"tintindex":0,"rotation":0,"texture":"#0"},"south":{"uv":[3.0,11.75,3.75,12.5],"tintindex":0,"rotation":0,"texture":"#0"},"north":{"uv":[2.25,11.75,3.0,12.5],"tintindex":0,"rotation":0,"texture":"#0"},"west":{"uv":[3.5,12.5,3.75,13.25],"tintindex":0,"rotation":0,"texture":"#0"},"up":{"uv":[13.25,3.75,12.5,3.5],"tintindex":0,"rotation":0,"texture":"#0"},"down":{"uv":[13.25,3.75,12.5,4.0],"tintindex":0,"rotation":0,"texture":"#0"}},"rotation":{"origin":[2.5,9.0,7.0000005],"angle":-45.0,"axis":"y"}}],"display":{"head":{"rotation":[0.0,0.0,0.0]},"firstperson_righthand":{"rotation":[0.0,0.0,0.0]},"thirdperson_lefthand":{"rotation":[0.0,-0.0,-0.0]},"firstperson_lefthand":{"rotation":[0.0,-0.0,-0.0]},"fixed":{"rotation":[0.0,0.0,0.0]},"ground":{"rotation":[0.0,0.0,0.0]},"thirdperson_righthand":{"rotation":[0.0,0.0,0.0]},"gui":{"rotation":[-150.0,-45.0,180.0]}}}