{"textures":{"0":"modelengine:entity/blood_staff_summon","particle":"#0"},"elements":[{"from":[4.3065634,5.7346334,5.166667],"to":[7.306563,8.734633,9.166667],"faces":{"east":{"uv":[9.0,7.25,10.0,8.0],"tintindex":0,"rotation":0,"texture":"#0"},"south":{"uv":[3.0,10.25,3.75,11.0],"tintindex":0,"rotation":0,"texture":"#0"},"north":{"uv":[2.25,10.25,3.0,11.0],"tintindex":0,"rotation":0,"texture":"#0"},"west":{"uv":[9.0,8.0,10.0,8.75],"tintindex":0,"rotation":0,"texture":"#0"},"up":{"uv":[9.25,10.0,8.5,9.0],"tintindex":0,"rotation":0,"texture":"#0"},"down":{"uv":[3.75,9.25,3.0,10.25],"tintindex":0,"rotation":0,"texture":"#0"}},"rotation":{"origin":[8.306563,6.7346334,8.166667],"angle":-22.5,"axis":"z"}},{"from":[8.693437,5.7346334,5.166667],"to":[11.693438,8.734633,9.166667],"faces":{"east":{"uv":[9.0,0.0,10.0,0.75],"tintindex":0,"rotation":0,"texture":"#0"},"south":{"uv":[1.5,10.25,2.25,11.0],"tintindex":0,"rotation":0,"texture":"#0"},"north":{"uv":[10.0,4.0,10.75,4.75],"tintindex":0,"rotation":0,"texture":"#0"},"west":{"uv":[9.0,0.75,10.0,1.5],"tintindex":0,"rotation":0,"texture":"#0"},"up":{"uv":[9.75,2.5,9.0,1.5],"tintindex":0,"rotation":0,"texture":"#0"},"down":{"uv":[9.75,2.5,9.0,3.5],"tintindex":0,"rotation":0,"texture":"#0"}},"rotation":{"origin":[7.693437,6.7346334,8.166667],"angle":22.5,"axis":"z"}},{"from":[7.0,6.1934376,4.166667],"to":[9.0,9.193438,9.166667],"faces":{"east":{"uv":[8.5,5.75,9.75,6.5],"tintindex":0,"rotation":0,"texture":"#0"},"south":{"uv":[4.5,10.75,5.0,11.5],"tintindex":0,"rotation":0,"texture":"#0"},"north":{"uv":[10.75,4.0,11.25,4.75],"tintindex":0,"rotation":0,"texture":"#0"},"west":{"uv":[8.5,6.5,9.75,7.25],"tintindex":0,"rotation":0,"texture":"#0"},"up":{"uv":[5.0,10.75,4.5,9.5],"tintindex":0,"rotation":0,"texture":"#0"},"down":{"uv":[7.75,10.0,7.25,11.25],"tintindex":0,"rotation":0,"texture":"#0"}}}],"display":{"head":{"rotation":[0.0,0.0,0.0]},"firstperson_righthand":{"rotation":[0.0,0.0,0.0]},"thirdperson_lefthand":{"rotation":[0.0,-0.0,-0.0]},"firstperson_lefthand":{"rotation":[0.0,-0.0,-0.0]},"fixed":{"rotation":[0.0,0.0,0.0]},"ground":{"rotation":[0.0,0.0,0.0]},"thirdperson_righthand":{"rotation":[0.0,0.0,0.0]},"gui":{"rotation":[-150.0,-45.0,180.0]}}}