{"credit":"Made with Blockbench","textures":{"0":"frostveil_genesis:wing_1_0","1":"frostveil_genesis:wing_1_1","2":"frostveil_genesis:axe_0"},"elements":[{"from":[-6.58202,1.75,8.53548],"to":[-3.08202,10.5,8.53548],"faces":{"north":{"uv":[10.666667,0,12.740741,5.185185],"texture":"#1"},"east":{"uv":[0,0,0,7.777784],"texture":"#0"},"south":{"uv":[12.740741,0,10.666667,5.185185],"texture":"#1"},"west":{"uv":[0,0,0,7.777784],"texture":"#0"},"up":{"uv":[3.111111,0,0,0],"texture":"#0"},"down":{"uv":[3.111111,0,0,0],"texture":"#0"}},"rotation":{"origin":[4.38345,6.125,3.81073],"axis":"y","angle":22.5,"rescale":false}},{"from":[-4.12017,1.75,7.58642],"to":[-0.62017,10.5,7.58642],"faces":{"north":{"uv":[2.37037,10.666667,4.444444,15.851852],"texture":"#1"},"east":{"uv":[0,0,0,7.777784],"texture":"#0"},"south":{"uv":[4.444444,10.666667,2.37037,15.851852],"texture":"#1"},"west":{"uv":[0,0,0,7.777784],"texture":"#0"},"up":{"uv":[3.111111,0,0,0],"texture":"#0"},"down":{"uv":[3.111111,0,0,0],"texture":"#0"}},"rotation":{"origin":[8,6.125,9.52449],"axis":"y","angle":45,"rescale":false}},{"from":[-2.96548,1.75,14.24924],"to":[0.53452,10.5,14.24924],"faces":{"north":{"uv":[0,10.666667,2.074074,15.851852],"texture":"#1"},"east":{"uv":[0,0,0,7.777784],"texture":"#0"},"south":{"uv":[2.074074,10.666667,0,15.851852],"texture":"#1"},"west":{"uv":[0,0,0,7.777784],"texture":"#0"},"up":{"uv":[3.111111,0,0,0],"texture":"#0"},"down":{"uv":[3.111111,0,0,0],"texture":"#0"}},"rotation":{"origin":[8,6.125,9.52449],"axis":"y","angle":-45,"rescale":false}},{"from":[-0.70528,1.75,11.03267],"to":[4.29472,10.5,11.03267],"faces":{"north":{"uv":[0,0,2.962963,5.185185],"texture":"#1"},"east":{"uv":[0,0,0,7.777784],"texture":"#0"},"south":{"uv":[2.962963,0,0,5.185185],"texture":"#1"},"west":{"uv":[0,0,0,7.777784],"texture":"#0"},"up":{"uv":[4.444444,0,0,0],"texture":"#0"},"down":{"uv":[4.444444,0,0,0],"texture":"#0"}},"rotation":{"origin":[8,6.125,9.52449],"axis":"y","angle":-22.5,"rescale":false}},{"from":[-0.70528,1.75,11.03267],"to":[4.29472,10.5,11.03267],"faces":{"north":{"uv":[2.962963,5.333333,5.925926,10.518519],"texture":"#1"},"east":{"uv":[0,0,0,7.777784],"texture":"#0"},"south":{"uv":[5.925926,5.333333,2.962963,10.518519],"texture":"#1"},"west":{"uv":[0,0,0,7.777784],"texture":"#0"},"up":{"uv":[4.444444,0,0,0],"texture":"#0"},"down":{"uv":[4.444444,0,0,0],"texture":"#0"}},"rotation":{"origin":[8,6.125,9.52449],"axis":"y","angle":45,"rescale":false}},{"from":[-0.70528,1.75,11.03267],"to":[4.29472,10.5,11.03267],"faces":{"north":{"uv":[0,5.333333,2.962963,10.518519],"texture":"#1"},"east":{"uv":[0,0,0,7.777784],"texture":"#0"},"south":{"uv":[2.962963,5.333333,0,10.518519],"texture":"#1"},"west":{"uv":[0,0,0,7.777784],"texture":"#0"},"up":{"uv":[4.444444,0,0,0],"texture":"#0"},"down":{"uv":[4.444444,0,0,0],"texture":"#0"}},"rotation":{"origin":[8,6.125,9.52449],"axis":"y","angle":22.5,"rescale":false}},{"from":[-0.70528,1.75,11.03267],"to":[4.29472,10.5,11.03267],"faces":{"north":{"uv":[2.962963,0,5.925926,5.185185],"texture":"#1"},"east":{"uv":[0,0,0,7.777784],"texture":"#0"},"south":{"uv":[5.925926,0,2.962963,5.185185],"texture":"#1"},"west":{"uv":[0,0,0,7.777784],"texture":"#0"},"up":{"uv":[4.444444,0,0,0],"texture":"#0"},"down":{"uv":[4.444444,0,0,0],"texture":"#0"}}},{"from":[-0.54012,-0.87801,6.935],"to":[-0.54012,0.25199,9.465],"faces":{"north":{"uv":[0,0,0,0.750003],"texture":"#0"},"east":{"uv":[12.666667,4.666667,14.333333,5.41667],"texture":"#0"},"south":{"uv":[0,0,0,0.750003],"texture":"#0"},"west":{"uv":[12.666667,6,14.333333,6.750003],"texture":"#0"},"up":{"uv":[0,1.666667,0,0],"texture":"#0"},"down":{"uv":[0,0,0,1.666667],"texture":"#0"}},"rotation":{"origin":[1.57488,-5.43801,8.2],"axis":"z","angle":-45,"rescale":false}},{"from":[2.59853,1.73639,6.1848],"to":[8.39653,5.53389,6.1848],"faces":{"north":{"uv":[0,0,3.874999,2.541665],"texture":"#0"},"east":{"uv":[0,0,0,2.541665],"texture":"#0"},"south":{"uv":[0,2.666667,3.874999,5.208332],"texture":"#0"},"west":{"uv":[0,0,0,2.541665],"texture":"#0"},"up":{"uv":[3.874999,0,0,0],"texture":"#0"},"down":{"uv":[3.874999,0,0,0],"texture":"#0"}},"rotation":{"origin":[7,5.72242,6.025],"axis":"y","angle":-22.5,"rescale":false}},{"from":[2.631,4.11376,6.46753],"to":[4.217,7.68226,6.46753],"faces":{"north":{"uv":[0,4.235295,1.882353,0],"texture":"#2","rotation":180},"east":{"uv":[0,4.235295,0,0],"texture":"#2","rotation":180},"south":{"uv":[2.125001,2.625001,4.007354,6.860296],"texture":"#2","rotation":180},"west":{"uv":[0,4.235295,0,0],"texture":"#2","rotation":180},"up":{"uv":[0,0,0,1.882353],"texture":"#2","rotation":270},"down":{"uv":[0,0,0,1.882353],"texture":"#2","rotation":90}},"rotation":{"origin":[4.2963,9.48246,6.9],"axis":"x","angle":22.5,"rescale":false}},{"from":[2.631,9.19315,5.07157],"to":[4.217,9.19315,8.64007],"faces":{"north":{"uv":[0,0,0,1.882353],"texture":"#2","rotation":270},"east":{"uv":[0,4.235295,0,0],"texture":"#2","rotation":90},"south":{"uv":[0,0,0,1.882353],"texture":"#2","rotation":270},"west":{"uv":[0,4.235295,0,0],"texture":"#2","rotation":270},"up":{"uv":[0,8.672794,1.882353,4.437499],"texture":"#2"},"down":{"uv":[2.125001,2.625001,4.007354,6.860296],"texture":"#2","rotation":180}},"rotation":{"origin":[4.2963,9.48246,6.9],"axis":"x","angle":-45,"rescale":false}},{"from":[2.91058,1.75,16.74721],"to":[2.91058,10.5,20.24721],"faces":{"north":{"uv":[0,0,0,7.777784],"texture":"#0"},"east":{"uv":[6.814815,10.666667,4.740741,15.851852],"texture":"#1"},"south":{"uv":[0,0,0,7.777784],"texture":"#0"},"west":{"uv":[4.740741,10.666667,6.814815,15.851852],"texture":"#1"},"up":{"uv":[3.111111,0,0,0],"texture":"#0","rotation":270},"down":{"uv":[3.111111,0,0,0],"texture":"#0","rotation":90}}},{"from":[3.59997,6.32618,7.11],"to":[6.42997,7.65618,7.11],"faces":{"north":{"uv":[11.333333,11.333333,13.208332,12.208332],"texture":"#0"},"east":{"uv":[0,0,0,0.874999],"texture":"#0"},"south":{"uv":[0,12,1.874999,12.874999],"texture":"#0"},"west":{"uv":[0,0,0,0.874999],"texture":"#0"},"up":{"uv":[1.874999,0,0,0],"texture":"#0"},"down":{"uv":[1.874999,0,0,0],"texture":"#0"}},"rotation":{"origin":[5.53997,5.54118,8.2],"axis":"z","angle":22.5,"rescale":false}},{"from":[3.7277,-0.68546,6.935],"to":[3.7277,4.44454,9.465],"faces":{"north":{"uv":[0,0,0,3.41667],"texture":"#0"},"east":{"uv":[0,5.333333,1.666667,8.750003],"texture":"#0"},"south":{"uv":[0,0,0,3.41667],"texture":"#0"},"west":{"uv":[2,5.333333,3.666667,8.750003],"texture":"#0"},"up":{"uv":[0,1.666667,0,0],"texture":"#0"},"down":{"uv":[0,0,0,1.666667],"texture":"#0"}},"rotation":{"origin":[5.8427,-1.24546,8.2],"axis":"z","angle":-22.5,"rescale":false}},{"from":[3.7277,-0.68546,9.465],"to":[5.7277,4.44454,9.465],"faces":{"north":{"uv":[4,6.666667,5.333333,10.083336],"texture":"#0"},"east":{"uv":[0,0,0,3.41667],"texture":"#0"},"south":{"uv":[6.666667,4,8,7.41667],"texture":"#0"},"west":{"uv":[0,0,0,3.41667],"texture":"#0"},"up":{"uv":[1.333333,0,0,0],"texture":"#0"},"down":{"uv":[1.333333,0,0,0],"texture":"#0"}},"rotation":{"origin":[5.8427,-1.24546,8.2],"axis":"z","angle":-22.5,"rescale":false}},{"from":[3.99961,1.75,9.49992],"to":[7.99961,10.5,9.49992],"faces":{"north":{"uv":[5.925926,0,8.296296,5.185185],"texture":"#1"},"east":{"uv":[0,0,0,7.777784],"texture":"#0"},"south":{"uv":[8.296296,0,5.925926,5.185185],"texture":"#1"},"west":{"uv":[0,0,0,7.777784],"texture":"#0"},"up":{"uv":[3.555556,0,0,0],"texture":"#0"},"down":{"uv":[3.555556,0,0,0],"texture":"#0"}}},{"from":[3.99961,1.75,9.49992],"to":[7.99961,10.5,9.49992],"faces":{"north":{"uv":[8.296296,0,10.666667,5.185185],"texture":"#1"},"east":{"uv":[0,0,0,7.777784],"texture":"#0"},"south":{"uv":[10.666667,0,8.296296,5.185185],"texture":"#1"},"west":{"uv":[0,0,0,7.777784],"texture":"#0"},"up":{"uv":[3.555556,0,0,0],"texture":"#0"},"down":{"uv":[3.555556,0,0,0],"texture":"#0"}},"rotation":{"origin":[8,6.125,9.52449],"axis":"y","angle":45,"rescale":false}},{"from":[3.99961,1.75,9.49992],"to":[7.99961,10.5,9.49992],"faces":{"north":{"uv":[5.925926,5.333333,8.296296,10.518519],"texture":"#1"},"east":{"uv":[0,0,0,7.777784],"texture":"#0"},"south":{"uv":[8.296296,5.333333,5.925926,10.518519],"texture":"#1"},"west":{"uv":[0,0,0,7.777784],"texture":"#0"},"up":{"uv":[3.555556,0,0,0],"texture":"#0"},"down":{"uv":[3.555556,0,0,0],"texture":"#0"}},"rotation":{"origin":[8,6.125,9.52449],"axis":"y","angle":22.5,"rescale":false}},{"from":[4.091,7.55494,7.11],"to":[6.921,8.88494,9.29],"faces":{"north":{"uv":[11.333333,8.666667,13.208332,9.541665],"texture":"#0"},"east":{"uv":[8,12,9.458335,12.874999],"texture":"#0"},"south":{"uv":[11.333333,10,13.208332,10.874999],"texture":"#0"},"west":{"uv":[3.333333,12.666667,4.791668,13.541665],"texture":"#0"},"up":{"uv":[11.208332,5.458335,9.333333,4],"texture":"#0"},"down":{"uv":[11.208332,6,9.333333,7.458335],"texture":"#0"}},"rotation":{"origin":[5.031,6.76994,8.2],"axis":"z","angle":22.5,"rescale":false}},{"from":[4.3756,9.19315,5.54737],"to":[5.9616,9.19315,9.11587],"faces":{"north":{"uv":[0,0,0,1.882353],"texture":"#2","rotation":270},"east":{"uv":[0,0,0,4.235295],"texture":"#2","rotation":90},"south":{"uv":[0,0,0,1.882353],"texture":"#2","rotation":270},"west":{"uv":[0,0,0,4.235295],"texture":"#2","rotation":270},"up":{"uv":[1.882353,4.437499,0,8.672794],"texture":"#2"},"down":{"uv":[4.007354,6.860296,2.125001,2.625001],"texture":"#2","rotation":180}},"rotation":{"origin":[4.2963,9.48246,6.9],"axis":"x","angle":-45,"rescale":false}},{"from":[4.3756,10.84431,8.67125],"to":[5.9616,14.41281,8.67125],"faces":{"north":{"uv":[1.882353,0,0,4.235295],"texture":"#2","rotation":180},"east":{"uv":[0,0,0,4.235295],"texture":"#2","rotation":180},"south":{"uv":[4.007354,6.860296,2.125001,2.625001],"texture":"#2","rotation":180},"west":{"uv":[0,0,0,4.235295],"texture":"#2","rotation":180},"up":{"uv":[0,0,0,1.882353],"texture":"#2","rotation":270},"down":{"uv":[0,0,0,1.882353],"texture":"#2","rotation":90}}},{"from":[4.516,4.60494,6.96],"to":[5.846,5.18494,9.44],"faces":{"north":{"uv":[13.333333,1.333333,14.208332,1.708332],"texture":"#0"},"east":{"uv":[11.333333,12.666667,13,13.041665],"texture":"#0"},"south":{"uv":[13.333333,2,14.208332,2.374999],"texture":"#0"},"west":{"uv":[0,13.333333,1.666667,13.708332],"texture":"#0"},"up":{"uv":[12.874999,1.666667,12,0],"texture":"#0"},"down":{"uv":[2.874999,12,2,13.666667],"texture":"#0"}},"rotation":{"origin":[6.631,3.54494,8.2],"axis":"z","angle":-45,"rescale":false}},{"from":[5.785,4.56,6.835],"to":[10.215,5.49,9.565],"faces":{"north":{"uv":[0,11.333333,2.958335,11.958335],"texture":"#0"},"east":{"uv":[0,10.666667,1.833333,11.291668],"texture":"#0"},"south":{"uv":[11.333333,4,14.291668,4.625001],"texture":"#0"},"west":{"uv":[12.666667,7.333333,14.5,7.958335],"texture":"#0"},"up":{"uv":[9.625001,1.833333,6.666667,0],"texture":"#0"},"down":{"uv":[9.625001,2,6.666667,3.833333],"texture":"#0"}}},{"from":[5.885,3.66,6.935],"to":[7.765,5.79,9.465],"faces":{"north":{"uv":[4,10.666667,5.250003,12.083336],"texture":"#0"},"east":{"uv":[6.666667,9.333333,8.333333,10.750003],"texture":"#0"},"south":{"uv":[11.333333,4.666667,12.583336,6.083336],"texture":"#0"},"west":{"uv":[9.333333,8,11,9.41667],"texture":"#0"},"up":{"uv":[3.91667,11,2.666667,9.333333],"texture":"#0"},"down":{"uv":[6.583336,10,5.333333,11.666667],"texture":"#0"}}},{"from":[5.985,3.91,7.185],"to":[10.015,8.79,9.215],"faces":{"north":{"uv":[4,0,6.666667,3.250003],"texture":"#0"},"east":{"uv":[5.333333,6.666667,6.666667,9.91667],"texture":"#0"},"south":{"uv":[4,3.333333,6.666667,6.583336],"texture":"#0"},"west":{"uv":[8,4,9.333333,7.250003],"texture":"#0"},"up":{"uv":[9.333333,9.333333,6.666667,8],"texture":"#0"},"down":{"uv":[2.666667,9.333333,0,10.666667],"texture":"#0"}}},{"from":[6.291,6.80494,6.86],"to":[7.721,7.83494,7.19],"faces":{"north":{"uv":[8,7.333333,8.958335,8],"texture":"#0"},"east":{"uv":[10.666667,13.333333,10.874999,14],"texture":"#0"},"south":{"uv":[10,12,10.958335,12.666667],"texture":"#0"},"west":{"uv":[13.333333,10.666667,13.541665,11.333333],"texture":"#0"},"up":{"uv":[8.291668,13.541665,7.333333,13.333333],"texture":"#0"},"down":{"uv":[9.625001,13.333333,8.666667,13.541665],"texture":"#0"}}},{"from":[6.291,7.83494,6.86],"to":[7.121,8.11494,7.19],"faces":{"north":{"uv":[0.666667,14,1.208332,14.166667],"texture":"#0"},"east":{"uv":[14,14.666667,14.208332,14.833333],"texture":"#0"},"south":{"uv":[1.333333,14,1.874999,14.166667],"texture":"#0"},"west":{"uv":[14.666667,14,14.874999,14.166667],"texture":"#0"},"up":{"uv":[12.541665,13.541665,12,13.333333],"texture":"#0"},"down":{"uv":[13.874999,12,13.333333,12.208332],"texture":"#0"}}},{"from":[6.82574,5.37367,6.61226],"to":[7.10539,5.60857,6.86714],"faces":{"north":{"uv":[15.333333,6,15.5,6.166667],"texture":"#0"},"east":{"uv":[6.666667,15.333333,6.833333,15.5],"texture":"#0"},"south":{"uv":[15.333333,6.666667,15.5,6.833333],"texture":"#0"},"west":{"uv":[7.333333,15.333333,7.5,15.5],"texture":"#0"},"up":{"uv":[15.5,7.5,15.333333,7.333333],"texture":"#0"},"down":{"uv":[8.166667,15.333333,8,15.5],"texture":"#0"}},"rotation":{"origin":[8,5.27758,6.5],"axis":"z","angle":-22.5,"rescale":false}},{"from":[6.90045,7.65749,6.885],"to":[7.30545,7.86249,7.19],"faces":{"north":{"uv":[15.333333,0,15.583336,0.125001],"texture":"#0"},"east":{"uv":[15.333333,8,15.541665,8.125001],"texture":"#0"},"south":{"uv":[0.666667,15.333333,0.91667,15.458335],"texture":"#0"},"west":{"uv":[8.666667,15.333333,8.874999,15.458335],"texture":"#0"},"up":{"uv":[2.250003,14.874999,2,14.666667],"texture":"#0"},"down":{"uv":[14.91667,2,14.666667,2.208332],"texture":"#0"}},"rotation":{"origin":[7.31545,7.72249,7.025],"axis":"z","angle":-45,"rescale":false}},{"from":[6.925,3.95,5.7],"to":[9.675,7.25,5.7],"faces":{"north":{"uv":[2.062501,0,4.886027,2.352942],"texture":"#2","rotation":270},"east":{"uv":[0,0,0,2.823526],"texture":"#2","rotation":180},"south":{"uv":[4.886027,0,2.062501,2.352942],"texture":"#2","rotation":90},"west":{"uv":[0,0,0,2.823526],"texture":"#2"},"up":{"uv":[0,0,0,2.352942],"texture":"#2","rotation":90},"down":{"uv":[0,0,0,2.352942],"texture":"#2","rotation":90}},"rotation":{"origin":[8.3,5.6,5.7],"axis":"x","angle":22.5,"rescale":false}},{"from":[7.10746,5.09898,6.5823],"to":[7.33238,5.33868,6.8971],"faces":{"north":{"uv":[15.333333,5.333333,15.5,5.5],"texture":"#0"},"east":{"uv":[12,14.666667,12.208332,14.833333],"texture":"#0"},"south":{"uv":[6,15.333333,6.166667,15.5],"texture":"#0"},"west":{"uv":[14.666667,12,14.874999,12.166667],"texture":"#0"},"up":{"uv":[12.833333,14.874999,12.666667,14.666667],"texture":"#0"},"down":{"uv":[14.833333,12.666667,14.666667,12.874999],"texture":"#0"}},"rotation":{"origin":[8,5.27758,6.5],"axis":"z","angle":45,"rescale":false}},{"from":[7.22167,5.07504,6.56232],"to":[7.66632,5.47454,6.91708],"faces":{"north":{"uv":[6,14,6.291668,14.250003],"texture":"#0"},"east":{"uv":[14,11.333333,14.250003,11.583336],"texture":"#0"},"south":{"uv":[6.666667,14,6.958335,14.250003],"texture":"#0"},"west":{"uv":[12,14,12.250003,14.250003],"texture":"#0"},"up":{"uv":[7.625001,14.250003,7.333333,14],"texture":"#0"},"down":{"uv":[8.291668,14,8,14.250003],"texture":"#0"}}},{"from":[7.32155,4.67554,6.56232],"to":[7.66632,5.07504,6.91708],"faces":{"north":{"uv":[9.333333,14,9.583336,14.250003],"texture":"#0"},"east":{"uv":[10,14,10.250003,14.250003],"texture":"#0"},"south":{"uv":[14,10,14.250003,10.250003],"texture":"#0"},"west":{"uv":[10.666667,14,10.91667,14.250003],"texture":"#0"},"up":{"uv":[14.250003,10.91667,14,10.666667],"texture":"#0"},"down":{"uv":[11.583336,14,11.333333,14.250003],"texture":"#0"}}},{"from":[7.38237,5.58724,6.5823],"to":[7.74711,5.86689,6.8971],"faces":{"north":{"uv":[8,14.666667,8.250003,14.833333],"texture":"#0"},"east":{"uv":[13.333333,14.666667,13.541665,14.833333],"texture":"#0"},"south":{"uv":[14.666667,8,14.91667,8.166667],"texture":"#0"},"west":{"uv":[14.666667,13.333333,14.874999,13.5],"texture":"#0"},"up":{"uv":[1.583336,14.874999,1.333333,14.666667],"texture":"#0"},"down":{"uv":[14.91667,1.333333,14.666667,1.541665],"texture":"#0"}},"rotation":{"origin":[8,5.27758,6.5],"axis":"z","angle":22.5,"rescale":false}},{"from":[7.49384,4.82958,6.44007],"to":[8.29284,5.62858,7.03932],"faces":{"north":{"uv":[8.666667,9.333333,9.208332,9.874999],"texture":"#0"},"east":{"uv":[3.333333,11.333333,3.750003,11.874999],"texture":"#0"},"south":{"uv":[2,10.666667,2.541665,11.208332],"texture":"#0"},"west":{"uv":[8,11.333333,8.41667,11.874999],"texture":"#0"},"up":{"uv":[3.874999,12.41667,3.333333,12],"texture":"#0"},"down":{"uv":[7.208332,13.333333,6.666667,13.750003],"texture":"#0"}},"rotation":{"origin":[8,5.12242,6.5],"axis":"z","angle":-45,"rescale":false}},{"from":[7.57374,4.90948,6.32022],"to":[8.21294,5.54868,6.44007],"faces":{"north":{"uv":[10,13.333333,10.41667,13.750003],"texture":"#0"},"east":{"uv":[10.666667,14.666667,10.750003,15.083336],"texture":"#0"},"south":{"uv":[13.333333,10,13.750003,10.41667],"texture":"#0"},"west":{"uv":[14.666667,10.666667,14.750003,11.083336],"texture":"#0"},"up":{"uv":[11.750003,14.750003,11.333333,14.666667],"texture":"#0"},"down":{"uv":[15.083336,11.333333,14.666667,11.41667],"texture":"#0"}},"rotation":{"origin":[8,5.12242,6.5],"axis":"z","angle":-45,"rescale":false}},{"from":[7.60347,1.73639,6.1848],"to":[13.40147,5.53389,6.1848],"faces":{"north":{"uv":[3.874999,0,0,2.541665],"texture":"#0"},"east":{"uv":[0,0,0,2.541665],"texture":"#0"},"south":{"uv":[3.874999,2.666667,0,5.208332],"texture":"#0"},"west":{"uv":[0,0,0,2.541665],"texture":"#0"},"up":{"uv":[0,0,3.874999,0],"texture":"#0"},"down":{"uv":[0,0,3.874999,0],"texture":"#0"}},"rotation":{"origin":[9,5.72242,6.025],"axis":"y","angle":22.5,"rescale":false}},{"from":[7.65364,4.98938,6.20037],"to":[8.13304,5.46878,6.32022],"faces":{"north":{"uv":[13.333333,13.333333,13.666667,13.666667],"texture":"#0"},"east":{"uv":[15.333333,1.333333,15.41667,1.666667],"texture":"#0"},"south":{"uv":[0,14,0.333333,14.333333],"texture":"#0"},"west":{"uv":[2,15.333333,2.083336,15.666667],"texture":"#0"},"up":{"uv":[15.666667,2.083336,15.333333,2],"texture":"#0"},"down":{"uv":[3,15.333333,2.666667,15.41667],"texture":"#0"}},"rotation":{"origin":[8,5.12242,6.5],"axis":"z","angle":-45,"rescale":false}},{"from":[7.66709,5.91881,6.59228],"to":[7.9819,6.23841,6.88712],"faces":{"north":{"uv":[5.333333,14.666667,5.541665,14.874999],"texture":"#0"},"east":{"uv":[14.666667,5.333333,14.874999,5.541665],"texture":"#0"},"south":{"uv":[6,14.666667,6.208332,14.874999],"texture":"#0"},"west":{"uv":[14.666667,6,14.874999,6.208332],"texture":"#0"},"up":{"uv":[6.874999,14.874999,6.666667,14.666667],"texture":"#0"},"down":{"uv":[14.874999,6.666667,14.666667,6.874999],"texture":"#0"}},"rotation":{"origin":[8,5.27758,6.5],"axis":"z","angle":45,"rescale":false}},{"from":[7.97543,1.75,9.52488],"to":[7.97543,10.5,13.52488],"faces":{"north":{"uv":[0,0,0,7.777784],"texture":"#0"},"east":{"uv":[5.925926,5.333333,2.962963,10.518519],"texture":"#1"},"south":{"uv":[0,0,0,7.777784],"texture":"#0"},"west":{"uv":[8.296296,5.333333,10.666667,10.518519],"texture":"#1"},"up":{"uv":[3.555556,0,0,0],"texture":"#0","rotation":270},"down":{"uv":[3.555556,0,0,0],"texture":"#0","rotation":90}},"rotation":{"origin":[8,6.125,9.52449],"axis":"y","angle":-22.5,"rescale":false}},{"from":[8.00039,1.75,9.49992],"to":[12.00039,10.5,9.49992],"faces":{"north":{"uv":[8.296296,5.333333,5.925926,10.518519],"texture":"#1"},"east":{"uv":[0,0,0,7.777784],"texture":"#0"},"south":{"uv":[5.925926,5.333333,8.296296,10.518519],"texture":"#1"},"west":{"uv":[0,0,0,7.777784],"texture":"#0"},"up":{"uv":[0,0,3.555556,0],"texture":"#0"},"down":{"uv":[0,0,3.555556,0],"texture":"#0"}},"rotation":{"origin":[8,6.125,9.52449],"axis":"y","angle":-22.5,"rescale":false}},{"from":[8.00039,1.75,9.49992],"to":[12.00039,10.5,9.49992],"faces":{"north":{"uv":[10.666667,0,8.296296,5.185185],"texture":"#1"},"east":{"uv":[0,0,0,7.777784],"texture":"#0"},"south":{"uv":[8.296296,0,10.666667,5.185185],"texture":"#1"},"west":{"uv":[0,0,0,7.777784],"texture":"#0"},"up":{"uv":[0,0,3.555556,0],"texture":"#0"},"down":{"uv":[0,0,3.555556,0],"texture":"#0"}},"rotation":{"origin":[8,6.125,9.52449],"axis":"y","angle":-45,"rescale":false}},{"from":[8.00039,1.75,9.49992],"to":[12.00039,10.5,9.49992],"faces":{"north":{"uv":[8.296296,0,5.925926,5.185185],"texture":"#1"},"east":{"uv":[0,0,0,7.777784],"texture":"#0"},"south":{"uv":[5.925926,0,8.296296,5.185185],"texture":"#1"},"west":{"uv":[0,0,0,7.777784],"texture":"#0"},"up":{"uv":[0,0,3.555556,0],"texture":"#0"},"down":{"uv":[0,0,3.555556,0],"texture":"#0"}}},{"from":[8.0181,5.91881,6.59228],"to":[8.33291,6.23841,6.88712],"faces":{"north":{"uv":[3.333333,14.666667,3.541665,14.874999],"texture":"#0"},"east":{"uv":[14.666667,3.333333,14.874999,3.541665],"texture":"#0"},"south":{"uv":[4,14.666667,4.208332,14.874999],"texture":"#0"},"west":{"uv":[14.666667,4,14.874999,4.208332],"texture":"#0"},"up":{"uv":[4.874999,14.874999,4.666667,14.666667],"texture":"#0"},"down":{"uv":[14.874999,4.666667,14.666667,4.874999],"texture":"#0"}},"rotation":{"origin":[8,5.27758,6.5],"axis":"z","angle":-45,"rescale":false}},{"from":[8.02457,1.75,9.52488],"to":[8.02457,10.5,13.52488],"faces":{"north":{"uv":[0,0,0,7.777784],"texture":"#0"},"east":{"uv":[10.666667,5.333333,8.296296,10.518519],"texture":"#1"},"south":{"uv":[0,0,0,7.777784],"texture":"#0"},"west":{"uv":[2.962963,5.333333,5.925926,10.518519],"texture":"#1"},"up":{"uv":[3.555556,0,0,0],"texture":"#0","rotation":270},"down":{"uv":[3.555556,0,0,0],"texture":"#0","rotation":90}},"rotation":{"origin":[8,6.125,9.52449],"axis":"y","angle":22.5,"rescale":false}},{"from":[8.235,3.66,6.935],"to":[10.115,5.79,9.465],"faces":{"north":{"uv":[6.666667,11.333333,7.91667,12.750003],"texture":"#0"},"east":{"uv":[10,0,11.666667,1.41667],"texture":"#0"},"south":{"uv":[11.333333,6.666667,12.583336,8.083336],"texture":"#0"},"west":{"uv":[10,2,11.666667,3.41667],"texture":"#0"},"up":{"uv":[9.91667,11.666667,8.666667,10],"texture":"#0"},"down":{"uv":[11.250003,10,10,11.666667],"texture":"#0"}}},{"from":[8.25289,5.58724,6.5823],"to":[8.61763,5.86689,6.8971],"faces":{"north":{"uv":[7.333333,14.666667,7.583336,14.833333],"texture":"#0"},"east":{"uv":[10,14.666667,10.208332,14.833333],"texture":"#0"},"south":{"uv":[14.666667,7.333333,14.91667,7.5],"texture":"#0"},"west":{"uv":[14.666667,10,14.874999,10.166667],"texture":"#0"},"up":{"uv":[0.250003,14.874999,0,14.666667],"texture":"#0"},"down":{"uv":[0.91667,14.666667,0.666667,14.874999],"texture":"#0"}},"rotation":{"origin":[8,5.27758,6.5],"axis":"z","angle":-22.5,"rescale":false}},{"from":[8.279,6.80494,6.86],"to":[9.709,7.83494,7.19],"faces":{"north":{"uv":[12.666667,8,13.625001,8.666667],"texture":"#0"},"east":{"uv":[11.333333,13.333333,11.541665,14],"texture":"#0"},"south":{"uv":[10,12.666667,10.958335,13.333333],"texture":"#0"},"west":{"uv":[13.333333,11.333333,13.541665,12],"texture":"#0"},"up":{"uv":[14.291668,8.874999,13.333333,8.666667],"texture":"#0"},"down":{"uv":[14.291668,9.333333,13.333333,9.541665],"texture":"#0"}}},{"from":[8.33368,4.67554,6.56232],"to":[8.67845,5.07504,6.91708],"faces":{"north":{"uv":[14,12,14.250003,12.250003],"texture":"#0"},"east":{"uv":[12.666667,14,12.91667,14.250003],"texture":"#0"},"south":{"uv":[14,12.666667,14.250003,12.91667],"texture":"#0"},"west":{"uv":[13.333333,14,13.583336,14.250003],"texture":"#0"},"up":{"uv":[14.250003,13.583336,14,13.333333],"texture":"#0"},"down":{"uv":[14.250003,14,14,14.250003],"texture":"#0"}}},{"from":[8.33368,5.07504,6.56232],"to":[8.77833,5.47454,6.91708],"faces":{"north":{"uv":[3.333333,14,3.625001,14.250003],"texture":"#0"},"east":{"uv":[14,8,14.250003,8.250003],"texture":"#0"},"south":{"uv":[4,14,4.291668,14.250003],"texture":"#0"},"west":{"uv":[8.666667,14,8.91667,14.250003],"texture":"#0"},"up":{"uv":[4.958335,14.250003,4.666667,14],"texture":"#0"},"down":{"uv":[5.625001,14,5.333333,14.250003],"texture":"#0"}}},{"from":[8.66762,5.09898,6.5823],"to":[8.89254,5.33868,6.8971],"faces":{"north":{"uv":[15.333333,2.666667,15.5,2.833333],"texture":"#0"},"east":{"uv":[8.666667,14.666667,8.874999,14.833333],"texture":"#0"},"south":{"uv":[3.333333,15.333333,3.5,15.5],"texture":"#0"},"west":{"uv":[14.666667,8.666667,14.874999,8.833333],"texture":"#0"},"up":{"uv":[9.5,14.874999,9.333333,14.666667],"texture":"#0"},"down":{"uv":[14.833333,9.333333,14.666667,9.541665],"texture":"#0"}},"rotation":{"origin":[8,5.27758,6.5],"axis":"z","angle":-45,"rescale":false}},{"from":[8.69455,7.65749,6.885],"to":[9.09955,7.86249,7.19],"faces":{"north":{"uv":[15.333333,0.666667,15.583336,0.791668],"texture":"#0"},"east":{"uv":[15.333333,8.666667,15.541665,8.791668],"texture":"#0"},"south":{"uv":[1.333333,15.333333,1.583336,15.458335],"texture":"#0"},"west":{"uv":[9.333333,15.333333,9.541665,15.458335],"texture":"#0"},"up":{"uv":[2.91667,14.874999,2.666667,14.666667],"texture":"#0"},"down":{"uv":[14.91667,2.666667,14.666667,2.874999],"texture":"#0"}},"rotation":{"origin":[8.68455,7.72249,7.025],"axis":"z","angle":45,"rescale":false}},{"from":[8.879,7.83494,6.86],"to":[9.709,8.11494,7.19],"faces":{"north":{"uv":[2,14,2.541665,14.166667],"texture":"#0"},"east":{"uv":[14.666667,14.666667,14.874999,14.833333],"texture":"#0"},"south":{"uv":[2.666667,14,3.208332,14.166667],"texture":"#0"},"west":{"uv":[0,15.333333,0.208332,15.5],"texture":"#0"},"up":{"uv":[13.208332,13.541665,12.666667,13.333333],"texture":"#0"},"down":{"uv":[13.874999,12.666667,13.333333,12.874999],"texture":"#0"}}},{"from":[8.89461,5.37367,6.61226],"to":[9.17426,5.60857,6.86714],"faces":{"north":{"uv":[15.333333,3.333333,15.5,3.5],"texture":"#0"},"east":{"uv":[4,15.333333,4.166667,15.5],"texture":"#0"},"south":{"uv":[15.333333,4,15.5,4.166667],"texture":"#0"},"west":{"uv":[4.666667,15.333333,4.833333,15.5],"texture":"#0"},"up":{"uv":[15.5,4.833333,15.333333,4.666667],"texture":"#0"},"down":{"uv":[5.5,15.333333,5.333333,15.5],"texture":"#0"}},"rotation":{"origin":[8,5.27758,6.5],"axis":"z","angle":22.5,"rescale":false}},{"from":[9.079,7.55494,7.11],"to":[11.909,8.88494,9.29],"faces":{"north":{"uv":[13.208332,8.666667,11.333333,9.541665],"texture":"#0"},"east":{"uv":[4.791668,12.666667,3.333333,13.541665],"texture":"#0"},"south":{"uv":[13.208332,10,11.333333,10.874999],"texture":"#0"},"west":{"uv":[9.458335,12,8,12.874999],"texture":"#0"},"up":{"uv":[9.333333,5.458335,11.208332,4],"texture":"#0"},"down":{"uv":[9.333333,6,11.208332,7.458335],"texture":"#0"}},"rotation":{"origin":[10.969,6.76994,8.2],"axis":"z","angle":-22.5,"rescale":false}},{"from":[9.57003,6.32618,7.11],"to":[12.40003,7.65618,7.11],"faces":{"north":{"uv":[13.208332,11.333333,11.333333,12.208332],"texture":"#0"},"east":{"uv":[0,0,0,0.874999],"texture":"#0"},"south":{"uv":[1.874999,12,0,12.874999],"texture":"#0"},"west":{"uv":[0,0,0,0.874999],"texture":"#0"},"up":{"uv":[0,0,1.874999,0],"texture":"#0"},"down":{"uv":[0,0,1.874999,0],"texture":"#0"}},"rotation":{"origin":[10.46003,5.54118,8.2],"axis":"z","angle":-22.5,"rescale":false}},{"from":[10.0384,9.19315,5.54737],"to":[11.6244,9.19315,9.11587],"faces":{"north":{"uv":[0,1.882353,0,0],"texture":"#2","rotation":270},"east":{"uv":[0,4.235295,0,0],"texture":"#2","rotation":270},"south":{"uv":[0,1.882353,0,0],"texture":"#2","rotation":270},"west":{"uv":[0,4.235295,0,0],"texture":"#2","rotation":90},"up":{"uv":[0,4.437499,1.882353,8.672794],"texture":"#2"},"down":{"uv":[2.125001,6.860296,4.007354,2.625001],"texture":"#2","rotation":180}},"rotation":{"origin":[11.7037,9.48246,6.9],"axis":"x","angle":-45,"rescale":false}},{"from":[10.0384,10.84431,8.67125],"to":[11.6244,14.41281,8.67125],"faces":{"north":{"uv":[0,0,1.882353,4.235295],"texture":"#2","rotation":180},"east":{"uv":[0,0,0,4.235295],"texture":"#2","rotation":180},"south":{"uv":[2.125001,6.860296,4.007354,2.625001],"texture":"#2","rotation":180},"west":{"uv":[0,0,0,4.235295],"texture":"#2","rotation":180},"up":{"uv":[0,1.882353,0,0],"texture":"#2","rotation":270},"down":{"uv":[0,1.882353,0,0],"texture":"#2","rotation":90}}},{"from":[10.154,4.60494,6.96],"to":[11.484,5.18494,9.44],"faces":{"north":{"uv":[13.333333,2.666667,14.208332,3.041665],"texture":"#0"},"east":{"uv":[13.333333,0,15,0.374999],"texture":"#0"},"south":{"uv":[13.333333,3.333333,14.208332,3.708332],"texture":"#0"},"west":{"uv":[13.333333,0.666667,15,1.041665],"texture":"#0"},"up":{"uv":[12.874999,3.666667,12,2],"texture":"#0"},"down":{"uv":[6.208332,12,5.333333,13.666667],"texture":"#0"}},"rotation":{"origin":[9.369,3.54494,8.2],"axis":"z","angle":45,"rescale":false}},{"from":[10.2723,-0.68546,9.465],"to":[12.2723,4.44454,9.465],"faces":{"north":{"uv":[5.333333,6.666667,4,10.083336],"texture":"#0"},"east":{"uv":[0,0,0,3.41667],"texture":"#0"},"south":{"uv":[8,4,6.666667,7.41667],"texture":"#0"},"west":{"uv":[0,0,0,3.41667],"texture":"#0"},"up":{"uv":[0,0,1.333333,0],"texture":"#0"},"down":{"uv":[0,0,1.333333,0],"texture":"#0"}},"rotation":{"origin":[10.1573,-1.24546,8.2],"axis":"z","angle":22.5,"rescale":false}},{"from":[11.70528,1.75,11.03267],"to":[16.70528,10.5,11.03267],"faces":{"north":{"uv":[5.925926,0,2.962963,5.185185],"texture":"#1"},"east":{"uv":[0,0,0,7.777784],"texture":"#0"},"south":{"uv":[2.962963,0,5.925926,5.185185],"texture":"#1"},"west":{"uv":[0,0,0,7.777784],"texture":"#0"},"up":{"uv":[0,0,4.444444,0],"texture":"#0"},"down":{"uv":[0,0,4.444444,0],"texture":"#0"}}},{"from":[11.70528,1.75,11.03267],"to":[16.70528,10.5,11.03267],"faces":{"north":{"uv":[2.962963,5.333333,0,10.518519],"texture":"#1"},"east":{"uv":[0,0,0,7.777784],"texture":"#0"},"south":{"uv":[0,5.333333,2.962963,10.518519],"texture":"#1"},"west":{"uv":[0,0,0,7.777784],"texture":"#0"},"up":{"uv":[0,0,4.444444,0],"texture":"#0"},"down":{"uv":[0,0,4.444444,0],"texture":"#0"}},"rotation":{"origin":[8,6.125,9.52449],"axis":"y","angle":-22.5,"rescale":false}},{"from":[11.70528,1.75,11.03267],"to":[16.70528,10.5,11.03267],"faces":{"north":{"uv":[5.925926,5.333333,2.962963,10.518519],"texture":"#1"},"east":{"uv":[0,0,0,7.777784],"texture":"#0"},"south":{"uv":[2.962963,5.333333,5.925926,10.518519],"texture":"#1"},"west":{"uv":[0,0,0,7.777784],"texture":"#0"},"up":{"uv":[0,0,4.444444,0],"texture":"#0"},"down":{"uv":[0,0,4.444444,0],"texture":"#0"}},"rotation":{"origin":[8,6.125,9.52449],"axis":"y","angle":-45,"rescale":false}},{"from":[11.70528,1.75,11.03267],"to":[16.70528,10.5,11.03267],"faces":{"north":{"uv":[2.962963,0,0,5.185185],"texture":"#1"},"east":{"uv":[0,0,0,7.777784],"texture":"#0"},"south":{"uv":[0,0,2.962963,5.185185],"texture":"#1"},"west":{"uv":[0,0,0,7.777784],"texture":"#0"},"up":{"uv":[0,0,4.444444,0],"texture":"#0"},"down":{"uv":[0,0,4.444444,0],"texture":"#0"}},"rotation":{"origin":[8,6.125,9.52449],"axis":"y","angle":22.5,"rescale":false}},{"from":[11.783,4.11376,6.46753],"to":[13.369,7.68226,6.46753],"faces":{"north":{"uv":[1.882353,4.235295,0,0],"texture":"#2","rotation":180},"east":{"uv":[0,4.235295,0,0],"texture":"#2","rotation":180},"south":{"uv":[4.007354,2.625001,2.125001,6.860296],"texture":"#2","rotation":180},"west":{"uv":[0,4.235295,0,0],"texture":"#2","rotation":180},"up":{"uv":[0,1.882353,0,0],"texture":"#2","rotation":270},"down":{"uv":[0,1.882353,0,0],"texture":"#2","rotation":90}},"rotation":{"origin":[11.7037,9.48246,6.9],"axis":"x","angle":22.5,"rescale":false}},{"from":[11.783,9.19315,5.07157],"to":[13.369,9.19315,8.64007],"faces":{"north":{"uv":[0,1.882353,0,0],"texture":"#2","rotation":270},"east":{"uv":[0,0,0,4.235295],"texture":"#2","rotation":270},"south":{"uv":[0,1.882353,0,0],"texture":"#2","rotation":270},"west":{"uv":[0,0,0,4.235295],"texture":"#2","rotation":90},"up":{"uv":[1.882353,8.672794,0,4.437499],"texture":"#2"},"down":{"uv":[4.007354,2.625001,2.125001,6.860296],"texture":"#2","rotation":180}},"rotation":{"origin":[11.7037,9.48246,6.9],"axis":"x","angle":-45,"rescale":false}},{"from":[12.2723,-0.68546,6.935],"to":[12.2723,4.44454,9.465],"faces":{"north":{"uv":[0,0,0,3.41667],"texture":"#0"},"east":{"uv":[3.666667,5.333333,2,8.750003],"texture":"#0"},"south":{"uv":[0,0,0,3.41667],"texture":"#0"},"west":{"uv":[1.666667,5.333333,0,8.750003],"texture":"#0"},"up":{"uv":[0,1.666667,0,0],"texture":"#0"},"down":{"uv":[0,0,0,1.666667],"texture":"#0"}},"rotation":{"origin":[10.1573,-1.24546,8.2],"axis":"z","angle":22.5,"rescale":false}},{"from":[13.08942,1.75,16.74721],"to":[13.08942,10.5,20.24721],"faces":{"north":{"uv":[0,0,0,7.777784],"texture":"#0"},"east":{"uv":[6.814815,10.666667,4.740741,15.851852],"texture":"#1"},"south":{"uv":[0,0,0,7.777784],"texture":"#0"},"west":{"uv":[4.740741,10.666667,6.814815,15.851852],"texture":"#1"},"up":{"uv":[3.111111,0,0,0],"texture":"#0","rotation":270},"down":{"uv":[3.111111,0,0,0],"texture":"#0","rotation":90}}},{"from":[15.46548,1.75,14.24924],"to":[18.96548,10.5,14.24924],"faces":{"north":{"uv":[2.074074,10.666667,0,15.851852],"texture":"#1"},"east":{"uv":[0,0,0,7.777784],"texture":"#0"},"south":{"uv":[0,10.666667,2.074074,15.851852],"texture":"#1"},"west":{"uv":[0,0,0,7.777784],"texture":"#0"},"up":{"uv":[0,0,3.111111,0],"texture":"#0"},"down":{"uv":[0,0,3.111111,0],"texture":"#0"}},"rotation":{"origin":[8,6.125,9.52449],"axis":"y","angle":45,"rescale":false}},{"from":[16.54012,-0.87801,6.935],"to":[16.54012,0.25199,9.465],"faces":{"north":{"uv":[0,0,0,0.750003],"texture":"#0"},"east":{"uv":[14.333333,6,12.666667,6.750003],"texture":"#0"},"south":{"uv":[0,0,0,0.750003],"texture":"#0"},"west":{"uv":[14.333333,4.666667,12.666667,5.41667],"texture":"#0"},"up":{"uv":[0,1.666667,0,0],"texture":"#0"},"down":{"uv":[0,0,0,1.666667],"texture":"#0"}},"rotation":{"origin":[14.42512,-5.43801,8.2],"axis":"z","angle":45,"rescale":false}},{"from":[16.62017,1.75,7.58642],"to":[20.12017,10.5,7.58642],"faces":{"north":{"uv":[4.444444,10.666667,2.37037,15.851852],"texture":"#1"},"east":{"uv":[0,0,0,7.777784],"texture":"#0"},"south":{"uv":[2.37037,10.666667,4.444444,15.851852],"texture":"#1"},"west":{"uv":[0,0,0,7.777784],"texture":"#0"},"up":{"uv":[0,0,3.111111,0],"texture":"#0"},"down":{"uv":[0,0,3.111111,0],"texture":"#0"}},"rotation":{"origin":[8,6.125,9.52449],"axis":"y","angle":-45,"rescale":false}},{"from":[19.08202,1.75,8.53548],"to":[22.58202,10.5,8.53548],"faces":{"north":{"uv":[12.740741,0,10.666667,5.185185],"texture":"#1"},"east":{"uv":[0,0,0,7.777784],"texture":"#0"},"south":{"uv":[10.666667,0,12.740741,5.185185],"texture":"#1"},"west":{"uv":[0,0,0,7.777784],"texture":"#0"},"up":{"uv":[0,0,3.111111,0],"texture":"#0"},"down":{"uv":[0,0,3.111111,0],"texture":"#0"}},"rotation":{"origin":[11.61655,6.125,3.81073],"axis":"y","angle":-22.5,"rescale":false}}],"display":{"thirdperson_righthand":{"rotation":[37,0,0],"translation":[0,3,1.75],"scale":[0.83,0.83,0.83]},"thirdperson_lefthand":{"rotation":[66.5,0,0],"translation":[-6,-1,10],"scale":[2.41,2.41,2.80648]},"firstperson_righthand":{"rotation":[-13.5,-180,0],"translation":[-9.25,5.5,4.75],"scale":[0.38,0.38,0.38]},"firstperson_lefthand":{"rotation":[-13.5,0,0],"translation":[-3.5,6.5,4.75],"scale":[0,0,0]},"ground":{"rotation":[45,0,0],"translation":[0.5,3,0],"scale":[0.4,0.4,0.4]},"gui":{"rotation":[-12,166,0],"translation":[0.5,3.5,0],"scale":[0.99,0.99,0.99]},"head":{"translation":[0,-54.25,-1],"scale":[4,4,4]},"fixed":{"translation":[0.75,6.5,-7.25],"scale":[1.83,1.83,1.83]}},"gui_light":"front","texture_size":[27,27],"mcmodels":"9976e35de4970ad7920429035f519b3b"}