{"format_version":"1.21.6","credit":"Made with Blockbench","texture_size":[64,64],"textures":{"0":"elitecreatures:flower_garden_animated_weapon_set/hoe_texture","1":"elitecreatures:flower_garden_animated_weapon_set/animation","particle":"elitecreatures:flower_garden_animated_weapon_set/hoe_texture"},"elements":[{"from":[6.5,13,6],"to":[9.5,16,10],"rotation":{"angle":0,"axis":"y","origin":[7.5,15,7]},"faces":{"north":{"uv":[10.25,4.25,11,5],"texture":"#0"},"east":{"uv":[11,4.25,12,5],"texture":"#0"},"south":{"uv":[10.25,4.25,11,5],"texture":"#0"},"west":{"uv":[11,4.25,12,5],"texture":"#0"},"up":{"uv":[10,5,10.75,6],"texture":"#0"},"down":{"uv":[10,5,10.75,6],"texture":"#0"}}},{"from":[6,13.75,5.25],"to":[10,14.75,11.25],"rotation":{"angle":-22.5,"axis":"x","origin":[8.5,14.25,8.5]},"faces":{"north":{"uv":[11.5,6,12.5,6.25],"texture":"#0"},"east":{"uv":[12,5.75,13.5,6],"texture":"#0"},"south":{"uv":[12.5,6,11.5,6.25],"texture":"#0"},"west":{"uv":[12,5.75,13.5,6],"texture":"#0"},"up":{"uv":[10.5,6,11.5,7.5],"texture":"#0"},"down":{"uv":[10.5,6,11.5,7.5],"texture":"#0"}}},{"from":[6.0125,13.75,4.75],"to":[9.9875,14.75,10.75],"rotation":{"angle":22.5,"axis":"x","origin":[8.5,14.25,8]},"faces":{"north":{"uv":[11.5,6,12.5,6.25],"texture":"#0"},"east":{"uv":[12,5.75,13.5,6],"texture":"#0"},"south":{"uv":[12.5,6,11.5,6.25],"texture":"#0"},"west":{"uv":[12,5.75,13.5,6],"texture":"#0"},"up":{"uv":[10.5,6,11.5,7.5],"texture":"#0"},"down":{"uv":[10.5,6,11.5,7.5],"texture":"#0"}}},{"from":[7.5,16,5],"to":[8.5,22,11],"rotation":{"angle":22.5,"axis":"z","origin":[8.5,16,8]},"faces":{"north":{"uv":[2.75,10,2.5,11.5],"texture":"#0"},"east":{"uv":[4.25,10.25,2.75,11.75],"texture":"#0"},"south":{"uv":[2.75,10,2.5,11.5],"texture":"#0"},"west":{"uv":[5.75,10.25,4.25,11.75],"texture":"#0"},"up":{"uv":[4.25,10,2.75,10.25],"rotation":90,"texture":"#0"},"down":{"uv":[4.25,10,2.75,10.25],"rotation":270,"texture":"#0"}}},{"from":[2.96447,24.53553,5],"to":[4.96447,25.53553,11],"rotation":{"angle":22.5,"axis":"z","origin":[8.5,16,8]},"faces":{"north":{"uv":[2.75,13.25,2.5,13.75],"rotation":90,"texture":"#0"},"east":{"uv":[4.25,13.25,2.75,13.5],"rotation":180,"texture":"#0"},"south":{"uv":[2.75,13.25,2.5,13.75],"rotation":270,"texture":"#0"},"west":{"uv":[4.25,13.25,2.75,13.5],"texture":"#0"},"up":{"uv":[4.25,13.5,2.75,14],"rotation":270,"texture":"#0"},"down":{"uv":[5.75,13.5,4.25,14],"rotation":270,"texture":"#0"}}},{"from":[-0.74264,19.24264,5],"to":[4.25736,20.24264,11],"rotation":{"angle":-22.5,"axis":"z","origin":[8.5,16,8]},"faces":{"north":{"uv":[2.75,11.75,2.5,13],"rotation":90,"texture":"#0"},"east":{"uv":[4.25,11.75,2.75,12],"rotation":180,"texture":"#0"},"south":{"uv":[2.75,11.75,2.5,13],"rotation":270,"texture":"#0"},"west":{"uv":[4.25,11.75,2.75,12],"texture":"#0"},"up":{"uv":[4.25,12,2.75,13.25],"rotation":270,"texture":"#0"},"down":{"uv":[5.75,12,4.25,13.25],"rotation":270,"texture":"#0"}}},{"from":[7.75,18,4],"to":[7.75,22,8],"rotation":{"angle":-22.5,"axis":"y","origin":[7.75,18,8]},"faces":{"north":{"uv":[9.75,3,10.75,2.75],"rotation":180,"texture":"#1"},"east":{"uv":[7.75,4.25,6.25,5.75],"rotation":270,"texture":"#1"},"south":{"uv":[9.75,2.75,10.75,2.5],"rotation":180,"texture":"#1"},"west":{"uv":[7.75,5.75,6.25,4.25],"rotation":270,"texture":"#1"},"up":{"uv":[8.5,7.5,7,8.5],"rotation":90,"texture":"#1"},"down":{"uv":[1.5,8.75,0,7.75],"rotation":270,"texture":"#1"}}},{"from":[7.75,18,8],"to":[7.75,22,12],"rotation":{"angle":-22.5,"axis":"z","origin":[7.75,18,8]},"faces":{"north":{"uv":[10.75,2.75,9.75,2.5],"rotation":180,"texture":"#1"},"east":{"uv":[7.75,5.75,6.25,4.25],"rotation":270,"texture":"#1"},"south":{"uv":[10.75,3,9.75,2.75],"rotation":180,"texture":"#1"},"west":{"uv":[7.75,4.25,6.25,5.75],"rotation":270,"texture":"#1"},"up":{"uv":[7,7.5,8.5,8.5],"rotation":90,"texture":"#1"},"down":{"uv":[0,8.75,1.5,7.75],"rotation":270,"texture":"#1"}}},{"from":[7.75,17,8],"to":[11.75,21,8],"rotation":{"angle":22.5,"axis":"y","origin":[7.75,17,8]},"faces":{"north":{"uv":[10,5.5,8.5,4],"rotation":270,"texture":"#1"},"east":{"uv":[10.75,3,9.75,2.75],"rotation":180,"texture":"#1"},"south":{"uv":[10,4,8.5,5.5],"rotation":270,"texture":"#1"},"west":{"uv":[10.75,2.75,9.75,2.5],"rotation":180,"texture":"#1"},"up":{"uv":[8.5,8.5,7,7.5],"rotation":180,"texture":"#1"},"down":{"uv":[1.5,7.75,0,8.75],"rotation":180,"texture":"#1"}}},{"from":[7.75,16,8],"to":[11.75,20,8],"rotation":{"angle":-22.5,"axis":"y","origin":[7.75,16,8]},"faces":{"north":{"uv":[8.5,5.5,10,4],"rotation":270,"texture":"#1"},"east":{"uv":[10.75,3,9.75,2.75],"rotation":180,"texture":"#1"},"south":{"uv":[8.5,4,10,5.5],"rotation":270,"texture":"#1"},"west":{"uv":[10.75,2.75,9.75,2.5],"rotation":180,"texture":"#1"},"up":{"uv":[8.5,8.5,7,7.5],"rotation":180,"texture":"#1"},"down":{"uv":[1.5,7.75,0,8.75],"rotation":180,"texture":"#1"}}},{"from":[7.75,14,4],"to":[7.75,18,8],"rotation":{"angle":45,"axis":"z","origin":[7.75,18,8]},"faces":{"north":{"uv":[9.75,2.75,10.75,3],"rotation":180,"texture":"#1"},"east":{"uv":[6.25,4.25,7.75,5.75],"rotation":270,"texture":"#1"},"south":{"uv":[9.75,2.5,10.75,2.75],"rotation":180,"texture":"#1"},"west":{"uv":[6.25,5.75,7.75,4.25],"rotation":270,"texture":"#1"},"up":{"uv":[1.5,7.75,0,8.75],"rotation":90,"texture":"#1"},"down":{"uv":[8.5,8.5,7,7.5],"rotation":270,"texture":"#1"}}},{"from":[7.75,18,8],"to":[11.75,18,12],"rotation":{"angle":-45,"axis":"z","origin":[7.75,18,8]},"faces":{"north":{"uv":[9.75,2.75,10.75,2.5],"rotation":90,"texture":"#1"},"east":{"uv":[7,8.5,8.5,7.5],"rotation":180,"texture":"#1"},"south":{"uv":[9.75,3,10.75,2.75],"rotation":270,"texture":"#1"},"west":{"uv":[0,7.75,1.5,8.75],"texture":"#1"},"up":{"uv":[6.25,5.75,7.75,4.25],"rotation":180,"texture":"#1"},"down":{"uv":[6.25,4.25,7.75,5.75],"rotation":180,"texture":"#1"}}},{"from":[8,1.25,6],"to":[8,15.25,12],"rotation":{"angle":22.5,"axis":"y","origin":[8,8.25,9]},"faces":{"north":{"uv":[0,0,0,1],"texture":"#0"},"east":{"uv":[0,4.25,1.5,7.75],"texture":"#0"},"south":{"uv":[0,0,0,1],"texture":"#0"},"west":{"uv":[1.5,4.25,0,7.75],"texture":"#0"},"up":{"uv":[2,0,0,0],"rotation":270,"texture":"#0"},"down":{"uv":[2,0,0,0],"rotation":90,"texture":"#0"}}},{"from":[8,1.25,4],"to":[8,15.25,10],"rotation":{"angle":-22.5,"axis":"y","origin":[8,8.25,7]},"faces":{"north":{"uv":[0,0,0,1],"texture":"#0"},"east":{"uv":[1.5,4.25,0,7.75],"texture":"#0"},"south":{"uv":[0,0,0,1],"texture":"#0"},"west":{"uv":[0,4.25,1.5,7.75],"texture":"#0"},"up":{"uv":[0,0,2,0],"rotation":270,"texture":"#0"},"down":{"uv":[0,0,2,0],"rotation":90,"texture":"#0"}}},{"from":[7,-10.75,6.5],"to":[10,-7.75,9.5],"rotation":{"angle":45,"axis":"z","origin":[8,-9.75,7.5]},"faces":{"north":{"uv":[9,4.25,9.75,5],"texture":"#0"},"east":{"uv":[2.5,8.75,3.25,9.5],"texture":"#0"},"south":{"uv":[9.75,4.25,9,5],"texture":"#0"},"west":{"uv":[3.5,8.75,4.25,9.5],"texture":"#0"},"up":{"uv":[5.25,9.5,4.5,8.75],"texture":"#0"},"down":{"uv":[9.75,2.25,9,3],"texture":"#0"}}},{"from":[7,-9,7],"to":[9,13,9],"rotation":{"angle":0,"axis":"y","origin":[7,-1,7]},"faces":{"north":{"uv":[1,10.5,1.5,16],"texture":"#0"},"east":{"uv":[2,10.5,2.5,16],"texture":"#0"},"south":{"uv":[1.5,10.5,1,16],"texture":"#0"},"west":{"uv":[1.5,10.5,2,16],"texture":"#0"},"up":{"uv":[10.25,7.5,9.75,7],"texture":"#0"},"down":{"uv":[10.25,7.5,9.75,8],"texture":"#0"}}},{"from":[11,2,6],"to":[11,2,10],"rotation":{"angle":-45,"axis":"z","origin":[11,2,6]},"faces":{"north":{"uv":[0,0,0,0],"texture":"#0"},"east":{"uv":[0,0,1,0],"texture":"#0"},"south":{"uv":[0,0,0,0],"texture":"#0"},"west":{"uv":[0,0,1,0],"texture":"#0"},"up":{"uv":[0,1,0,0],"texture":"#0"},"down":{"uv":[0,0,0,1],"texture":"#0"}}},{"from":[11,2,6],"to":[11,2,10],"rotation":{"angle":-22.5,"axis":"z","origin":[11,2,6]},"faces":{"north":{"uv":[0,0,0,0],"texture":"#0"},"east":{"uv":[0,0,1,0],"texture":"#0"},"south":{"uv":[0,0,0,0],"texture":"#0"},"west":{"uv":[0,0,1,0],"texture":"#0"},"up":{"uv":[0,1,0,0],"texture":"#0"},"down":{"uv":[0,0,0,1],"texture":"#0"}}},{"from":[11,-2,8],"to":[20,-2,8],"rotation":{"angle":0,"axis":"y","origin":[11,0,8]},"faces":{"north":{"uv":[0,0,2.25,0],"texture":"#0"},"east":{"uv":[0,0,0,0],"texture":"#0"},"south":{"uv":[0,0,2.25,0],"texture":"#0"},"west":{"uv":[0,0,0,0],"texture":"#0"},"up":{"uv":[2.25,0,0,0],"texture":"#0"},"down":{"uv":[2.25,0,0,0],"texture":"#0"}}},{"from":[11,-1,7],"to":[19,-1,7],"rotation":{"angle":-22.5,"axis":"z","origin":[11,2,7]},"faces":{"north":{"uv":[0,0,2,0],"texture":"#0"},"east":{"uv":[0,0,0,0],"texture":"#0"},"south":{"uv":[0,0,2,0],"texture":"#0"},"west":{"uv":[0,0,0,0],"texture":"#0"},"up":{"uv":[2,0,0,0],"texture":"#0"},"down":{"uv":[2,0,0,0],"texture":"#0"}}},{"from":[5,-16,8],"to":[11,-16,8],"rotation":{"angle":0,"axis":"y","origin":[7,-16,7]},"faces":{"north":{"uv":[0,0,1.5,0],"texture":"#0"},"east":{"uv":[0,0,0,0],"texture":"#0"},"south":{"uv":[0,0,1.5,0],"texture":"#0"},"west":{"uv":[0,0,0,0],"texture":"#0"},"up":{"uv":[1.5,0,0,0],"texture":"#0"},"down":{"uv":[1.5,0,0,0],"texture":"#0"}}},{"from":[7,-10,7],"to":[9,-10,9],"rotation":{"angle":0,"axis":"y","origin":[7,-2,7]},"faces":{"north":{"uv":[0,0,0.5,0],"texture":"#0"},"east":{"uv":[0,0,0.5,0],"texture":"#0"},"south":{"uv":[0,0,0.5,0],"texture":"#0"},"west":{"uv":[0,0,0.5,0],"texture":"#0"},"up":{"uv":[10.25,9,9.75,8.5],"texture":"#0"},"down":{"uv":[9.5,9.75,9,10.25],"texture":"#0"}}}],"gui_light":"front","display":{"thirdperson_righthand":{"rotation":[0,-90,0],"translation":[0,5.25,1.75],"scale":[0.65,0.65,0.65]},"thirdperson_lefthand":{"rotation":[0,90,0],"translation":[0,5.25,1.75],"scale":[0.65,0.65,0.65]},"firstperson_righthand":{"rotation":[-10,-83,2],"translation":[6.5,5.25,-4.25],"scale":[0.51211,0.51211,0.51211]},"firstperson_lefthand":{"rotation":[-10,97,2],"translation":[6.5,5.25,-4.25],"scale":[0.51211,0.51211,0.51211]},"ground":{"rotation":[90,0,90],"translation":[-1.5,9,0],"scale":[0.55,0.55,0.55]},"gui":{"rotation":[0,0,45],"translation":[0.75,0.75,-1.5],"scale":[0.51758,0.51758,0.51758]},"head":{"scale":[0,0,0]},"fixed":{"translation":[0,7.5,-2],"scale":[1.4,1.4,1.4]}},"groups":[{"name":"group","origin":[8,8,8],"color":0,"children":[0,1,2,{"name":"group","origin":[8.5,16,8],"color":0,"children":[3,{"name":"group","origin":[8.5,22,8],"color":0,"children":[4,5]}]},{"name":"group","origin":[8,3,7],"color":0,"children":[6,7,8,9,10,11]},12,13,14,15]},{"name":"group","origin":[8,8,8],"color":0,"children":[16,17,18,19,20,21]}],"mcmodels":"aa9b47c9c0f055b0df118fa1ba49f96d"}