{"textures":{"0":"modelengine:entity/ice_freeze_fx","particle":"#0"},"elements":[{"from":[4.18198,7.5251265,7.0],"to":[9.18198,12.525126,15.0],"faces":{"east":{"uv":[5.0,8.0,9.0,10.5],"tintindex":0,"rotation":0,"texture":"#0"},"south":{"uv":[12.5,0.0,15.0,2.5],"tintindex":0,"rotation":0,"texture":"#0"},"north":{"uv":[12.0,10.5,14.5,13.0],"tintindex":0,"rotation":0,"texture":"#0"},"west":{"uv":[9.0,8.0,13.0,10.5],"tintindex":0,"rotation":0,"texture":"#0"},"up":{"uv":[12.5,4.0,10.0,0.0],"tintindex":0,"rotation":0,"texture":"#0"},"down":{"uv":[12.5,4.0,10.0,8.0],"tintindex":0,"rotation":0,"texture":"#0"}},"rotation":{"origin":[7.1819806,7.5251265,9.0],"angle":45.0,"axis":"z"}},{"from":[8.06066,7.4748735,7.0],"to":[12.06066,11.474874,14.0],"faces":{"east":{"uv":[5.0,10.5,8.5,12.5],"tintindex":0,"rotation":0,"texture":"#0"},"south":{"uv":[6.0,12.5,8.0,14.5],"tintindex":0,"rotation":0,"texture":"#0"},"north":{"uv":[12.5,5.0,14.5,7.0],"tintindex":0,"rotation":0,"texture":"#0"},"west":{"uv":[8.5,10.5,12.0,12.5],"tintindex":0,"rotation":0,"texture":"#0"},"up":{"uv":[2.0,15.5,0.0,12.0],"tintindex":0,"rotation":0,"texture":"#0"},"down":{"uv":[4.0,12.0,2.0,15.5],"tintindex":0,"rotation":0,"texture":"#0"}}},{"from":[5.0606604,4.4748735,5.0],"to":[11.06066,12.474874,13.0],"faces":{"east":{"uv":[0.0,0.0,4.0,4.0],"tintindex":0,"rotation":0,"texture":"#0"},"south":{"uv":[4.0,4.0,7.0,8.0],"tintindex":0,"rotation":0,"texture":"#0"},"north":{"uv":[4.0,0.0,7.0,4.0],"tintindex":0,"rotation":0,"texture":"#0"},"west":{"uv":[0.0,4.0,4.0,8.0],"tintindex":0,"rotation":0,"texture":"#0"},"up":{"uv":[10.0,4.0,7.0,0.0],"tintindex":0,"rotation":0,"texture":"#0"},"down":{"uv":[10.0,4.0,7.0,8.0],"tintindex":0,"rotation":0,"texture":"#0"}}},{"from":[7.0606604,4.4748735,13.0],"to":[11.06066,9.474874,16.0],"faces":{"east":{"uv":[8.0,12.5,9.5,15.0],"tintindex":0,"rotation":0,"texture":"#0"},"south":{"uv":[4.0,12.5,6.0,15.0],"tintindex":0,"rotation":0,"texture":"#0"},"north":{"uv":[12.5,2.5,14.5,5.0],"tintindex":0,"rotation":0,"texture":"#0"},"west":{"uv":[9.5,12.5,11.0,15.0],"tintindex":0,"rotation":0,"texture":"#0"},"up":{"uv":[15.0,8.5,13.0,7.0],"tintindex":0,"rotation":0,"texture":"#0"},"down":{"uv":[15.0,8.5,13.0,10.0],"tintindex":0,"rotation":0,"texture":"#0"}}}],"display":{"head":{"rotation":[0.0,0.0,0.0]},"firstperson_righthand":{"rotation":[0.0,0.0,0.0]},"thirdperson_lefthand":{"rotation":[0.0,-0.0,-0.0]},"firstperson_lefthand":{"rotation":[0.0,-0.0,-0.0]},"fixed":{"rotation":[0.0,0.0,0.0]},"ground":{"rotation":[0.0,0.0,0.0]},"thirdperson_righthand":{"rotation":[0.0,0.0,0.0]},"gui":{"rotation":[-150.0,-45.0,180.0]}}}