{"textures":{"0":"modelengine:entity/pet_knight_ender","particle":"#0"},"elements":[{"from":[3.5,5.543291,7.559699],"to":[12.5,5.543291,15.559698],"faces":{"up":{"uv":[1.5,3.125,0.375,2.125],"tintindex":0,"rotation":0,"texture":"#0"},"down":{"uv":[1.5,2.125,0.375,3.125],"tintindex":0,"rotation":0,"texture":"#0"}},"rotation":{"origin":[8.0,5.543291,14.059699],"angle":22.5,"axis":"x"}}],"display":{"head":{"rotation":[0.0,0.0,0.0]},"firstperson_righthand":{"rotation":[0.0,0.0,0.0]},"thirdperson_lefthand":{"rotation":[0.0,-0.0,-0.0]},"firstperson_lefthand":{"rotation":[0.0,-0.0,-0.0]},"fixed":{"rotation":[0.0,0.0,0.0]},"ground":{"rotation":[0.0,0.0,0.0]},"thirdperson_righthand":{"rotation":[0.0,0.0,0.0]},"gui":{"rotation":[-150.0,-45.0,180.0]}}}