{"credit":"Made with Blockbench","texture_size":[64,64],"textures":{"0":"redstone_labs:farming_expansion/overworld/crops/chilli_stages","particle":"redstone_labs:farming_expansion/overworld/crops/chilli_stages"},"elements":[{"from":[8,0,-0.5],"to":[8,16,17.5],"rotation":{"angle":-45,"axis":"y","origin":[8,0,8]},"faces":{"north":{"uv":[4,4,0,8],"texture":"#0"},"east":{"uv":[4,4,0,8],"texture":"#0"},"south":{"uv":[4,4,0,8],"texture":"#0"},"west":{"uv":[4,4,0,8],"texture":"#0"},"up":{"uv":[4,4,0,8],"texture":"#0"},"down":{"uv":[4,4,0,8],"texture":"#0"}}},{"from":[8,0,-0.5],"to":[8,16,17.5],"rotation":{"angle":45,"axis":"y","origin":[8,0,8]},"faces":{"north":{"uv":[4,4,0,8],"texture":"#0"},"east":{"uv":[4,4,0,8],"texture":"#0"},"south":{"uv":[4,4,0,8],"texture":"#0"},"west":{"uv":[4,4,0,8],"texture":"#0"},"up":{"uv":[4,4,0,8],"texture":"#0"},"down":{"uv":[4,4,0,8],"texture":"#0"}}}],"display":{"fixed":{"rotation":[-90,0,0],"translation":[0,0,-15.5],"scale":[2,2,2]}},"groups":[{"name":"bone","origin":[8,0,8],"color":0,"children":[0,1]}],"mcmodels":"f2e0e0ea605cea6828e78971c675916f"}