{"textures":{"1":"modelengine:entity/vfx_air_dragon","particle":"#1"},"elements":[{"from":[-5.9336395,5.15,-0.77149963],"to":[-5.9336395,10.85,5.2285],"faces":{"east":{"uv":[6.0,0.0,3.0,2.75],"tintindex":0,"rotation":0,"texture":"#1"},"west":{"uv":[3.0,0.0,6.0,2.75],"tintindex":0,"rotation":0,"texture":"#1"}},"rotation":{"origin":[-5.9336395,8.0,2.2285],"angle":-22.5,"axis":"y"}},{"from":[-2.6643343,5.15,-5.66436],"to":[-2.6643343,10.85,0.33563995],"faces":{"east":{"uv":[6.0,2.75,3.0,5.5],"tintindex":0,"rotation":0,"texture":"#1"},"west":{"uv":[3.0,2.75,6.0,5.5],"tintindex":0,"rotation":0,"texture":"#1"}},"rotation":{"origin":[-2.6643343,8.0,-2.66436],"angle":-45.0,"axis":"y"}},{"from":[-7.081664,5.15,5.000025],"to":[-7.081664,10.85,11.000025],"faces":{"east":{"uv":[3.0,2.75,0.0,5.5],"tintindex":0,"rotation":0,"texture":"#1"},"west":{"uv":[0.0,2.75,3.0,5.5],"tintindex":0,"rotation":0,"texture":"#1"}}},{"from":[5.00005,5.15,-7.081995],"to":[11.00005,10.85,-7.081995],"faces":{"south":{"uv":[3.0,0.0,0.0,2.75],"tintindex":0,"rotation":0,"texture":"#1"},"north":{"uv":[0.0,0.0,3.0,2.75],"tintindex":0,"rotation":0,"texture":"#1"}}},{"from":[-0.7715845,5.15,-7.08197],"to":[5.228415,10.85,-7.08197],"faces":{"south":{"uv":[3.0,5.5,0.0,8.25],"tintindex":0,"rotation":0,"texture":"#1"},"north":{"uv":[0.0,5.5,3.0,8.25],"tintindex":0,"rotation":0,"texture":"#1"}},"rotation":{"origin":[5.114175,8.0,-6.5079603],"angle":22.5,"axis":"y"}}],"display":{"head":{"rotation":[0.0,0.0,0.0]},"firstperson_righthand":{"rotation":[0.0,0.0,0.0]},"thirdperson_lefthand":{"rotation":[0.0,-0.0,-0.0]},"firstperson_lefthand":{"rotation":[0.0,-0.0,-0.0]},"fixed":{"rotation":[0.0,0.0,0.0]},"ground":{"rotation":[0.0,0.0,0.0]},"thirdperson_righthand":{"rotation":[0.0,0.0,0.0]},"gui":{"rotation":[-150.0,-45.0,180.0]}}}