{"textures":{"0":"modelengine:entity/fx_crow","particle":"#0"},"elements":[{"from":[7.2625,4.5,9.5],"to":[7.2625,8.5,15.5],"faces":{"east":{"uv":[3.25,2.0,1.75,3.0],"tintindex":0,"rotation":0,"texture":"#0"},"west":{"uv":[1.75,2.0,3.25,3.0],"tintindex":0,"rotation":0,"texture":"#0"}}},{"from":[7.2375,5.5,7.5],"to":[8.2375,8.5,12.5],"faces":{"east":{"uv":[5.25,4.5,4.0,5.25],"tintindex":0,"rotation":0,"texture":"#0"},"south":{"uv":[7.0,6.75,7.25,7.5],"tintindex":0,"rotation":0,"texture":"#0"},"north":{"uv":[7.0,5.75,7.25,6.5],"tintindex":0,"rotation":0,"texture":"#0"},"west":{"uv":[4.0,4.5,5.25,5.25],"tintindex":0,"rotation":0,"texture":"#0"},"up":{"uv":[7.0,5.5,6.75,4.25],"tintindex":0,"rotation":0,"texture":"#0"},"down":{"uv":[0.25,7.0,0.0,8.25],"tintindex":0,"rotation":0,"texture":"#0"}}}],"display":{"head":{"rotation":[0.0,0.0,0.0]},"firstperson_righthand":{"rotation":[0.0,0.0,0.0]},"thirdperson_lefthand":{"rotation":[0.0,-0.0,-0.0]},"firstperson_lefthand":{"rotation":[0.0,-0.0,-0.0]},"fixed":{"rotation":[0.0,0.0,0.0]},"ground":{"rotation":[0.0,0.0,0.0]},"thirdperson_righthand":{"rotation":[0.0,0.0,0.0]},"gui":{"rotation":[-150.0,-45.0,180.0]}}}