{"format_version":"1.21.6","credit":"Made with Blockbench","texture_size":[64,64],"textures":{"9":"khan_rogue_class:khan_rogue_class/rogue_helmet"},"elements":[{"from":[3.74,0.24,3.74],"to":[12.24,2.74,12.24],"rotation":{"angle":0,"axis":"y","origin":[8,1,8]},"faces":{"north":{"uv":[4,5,6.25,5.75],"texture":"#9"},"east":{"uv":[4,5.75,6.25,6.5],"texture":"#9"},"south":{"uv":[6.25,0,8.5,0.75],"texture":"#9"},"west":{"uv":[6.25,0.75,8.5,1.5],"texture":"#9"},"up":{"uv":[2.25,2.25,0,0],"texture":"#9"},"down":{"uv":[2.25,2.25,0,4.5],"texture":"#9"}}},{"from":[3.725,-1.825,3.725],"to":[12.275,8.725,12.275],"rotation":{"angle":0,"axis":"y","origin":[8,4.45,8]},"faces":{"north":{"uv":[2.25,0,4.25,2.5],"texture":"#9"},"east":{"uv":[2.25,2.5,4.25,5],"texture":"#9"},"south":{"uv":[4.25,0,6.25,2.5],"texture":"#9"},"west":{"uv":[4.25,2.5,6.25,5],"texture":"#9"},"up":{"uv":[2,6.5,0,4.5],"texture":"#9"},"down":{"uv":[4,5,2,7],"texture":"#9"}}}],"display":{"firstperson_righthand":{"rotation":[166.83,42.93,-161.04],"translation":[0,5,0],"scale":[0.73,0.73,0.73]},"firstperson_lefthand":{"rotation":[166.83,42.93,-161.04],"translation":[0,5,0],"scale":[0.73,0.73,0.73]},"ground":{"rotation":[10,0,0],"translation":[0,7,0]},"gui":{"rotation":[177.85,32.38,-157.17],"translation":[1.25,4.25,0],"scale":[1.07,1.07,1.07]},"head":{"translation":[0,6,0],"scale":[1.69,1.69,1.69]},"fixed":{"translation":[0,5,0],"scale":[1.27,1.27,1.27]},"on_shelf":{"rotation":[-180,0,-180],"scale":[1.42,1.42,1.42]}},"groups":[{"name":"rogue_helmet","origin":[8,-2.2,8],"color":0,"children":[0,1]}],"mcmodels":"ebcdfe0e7868e87776f3f32857a16b00"}