{"textures":{"0":"modelengine:entity/thunder_slash_3","particle":"#0"},"elements":[{"from":[6.94616,8.51898,-5.38863],"to":[20.94616,8.51898,22.611372],"faces":{"up":{"uv":[1.0,15.75,3.125,10.0],"tintindex":0,"rotation":0,"texture":"#0"},"down":{"uv":[1.0,10.0,3.125,15.75],"tintindex":0,"rotation":0,"texture":"#0"}},"rotation":{"origin":[8.0,8.0,8.0],"angle":22.5,"axis":"y"}}],"display":{"head":{"rotation":[0.0,0.0,0.0]},"firstperson_righthand":{"rotation":[0.0,0.0,0.0]},"thirdperson_lefthand":{"rotation":[0.0,-0.0,-0.0]},"firstperson_lefthand":{"rotation":[0.0,-0.0,-0.0]},"fixed":{"rotation":[0.0,0.0,0.0]},"ground":{"rotation":[0.0,0.0,0.0]},"thirdperson_righthand":{"rotation":[0.0,0.0,0.0]},"gui":{"rotation":[-150.0,-45.0,180.0]}}}